_portaudio.cpython-37m-i386-linux-gnu.so
pyaudio.py
pyaudio_wheels.libs/libportaudio-3e405a6b.so.2.0.0
pyaudio_wheels-0.0.1.dist-info/WHEEL
pyaudio_wheels-0.0.1.dist-info/top_level.txt
pyaudio_wheels-0.0.1.dist-info/RECORD
pyaudio_wheels-0.0.1.dist-info/METADATA
