Metadata-Version: 2.1
Name: pyaudio-wheels
Version: 0.0.1
Summary: PortAudio Python Bindings
Home-page: http://people.csail.mit.edu/hubert/pyaudio/
Author: Hubert Pham
Author-email: UNKNOWN
License: UNKNOWN
Platform: UNKNOWN
